<?xml version='1.0' encoding='UTF-8'?><factura version='1.1.0' id='comprobante'><infoTributaria><ambiente>2</ambiente><tipoEmision>1</tipoEmision><razonSocial>GALO MAURICIO VARGAS AGUILAR</razonSocial><nombreComercial>NOVEDADES VARGAS</nombreComercial><ruc>1104264039001</ruc><claveAcceso>0302202301110426403900120010010000027601234567815</claveAcceso><codDoc>01</codDoc><estab>001</estab><ptoEmi>001</ptoEmi><secuencial>000002760</secuencial><dirMatriz>CDLA ALBORADA AV RODOLFO BAQUERIZO NAZUR MZ 902 Y BENJAMIN CARRION</dirMatriz></infoTributaria><infoFactura><fechaEmision>03/02/2023</fechaEmision><dirEstablecimiento>GUAYAQUIL</dirEstablecimiento><obligadoContabilidad>NO</obligadoContabilidad><tipoIdentificacionComprador>04</tipoIdentificacionComprador><razonSocialComprador>CERVANTES CEVALLOS CARLOS ANGEL</razonSocialComprador><identificacionComprador>1002078226001</identificacionComprador><totalSinImpuestos>60.05</totalSinImpuestos><totalDescuento>0</totalDescuento><totalConImpuestos><totalImpuesto><codigo>2</codigo><codigoPorcentaje>2</codigoPorcentaje><baseImponible>60.05</baseImponible><valor>7.21</valor></totalImpuesto></totalConImpuestos><propina>0.00</propina><importeTotal>67.26</importeTotal><moneda>DOLAR</moneda><pagos><pago><formaPago>01</formaPago><total>67.26</total></pago></pagos></infoFactura><detalles><detalle><codigoPrincipal>FAM.TIP.521</codigoPrincipal><descripcion>CHE-344581 ATRAPA PELUSAS PARA LAVADORA</descripcion><cantidad>1</cantidad><precioUnitario>60.05</precioUnitario><descuento>0</descuento><precioTotalSinImpuesto>60.05</precioTotalSinImpuesto><impuestos><impuesto><codigo>2</codigo><codigoPorcentaje>2</codigoPorcentaje><tarifa>12</tarifa><baseImponible>60.05</baseImponible><valor>7.21</valor></impuesto></impuestos></detalle></detalles><infoAdicional><campoAdicional nombre='Direccion'>TJNJNKK</campoAdicional><campoAdicional nombre='Telefono'>233626</campoAdicional><campoAdicional nombre='Email'>carmichi12@hotmail.com</campoAdicional></infoAdicional></factura>