<?xml version='1.0' encoding='UTF-8'?><factura version='1.1.0' id='comprobante'><infoTributaria><ambiente>2</ambiente><tipoEmision>1</tipoEmision><razonSocial>GALO MAURICIO VARGAS AGUILAR</razonSocial><nombreComercial>NOVEDADES VARGAS</nombreComercial><ruc>1104264039001</ruc><claveAcceso>1912202201110426403900120010010000005001234567816</claveAcceso><codDoc>01</codDoc><estab>001</estab><ptoEmi>001</ptoEmi><secuencial>000000500</secuencial><dirMatriz>CDLA ALBORADA AV RODOLFO BAQUERIZO NAZUR MZ 902 Y BENJAMIN CARRION</dirMatriz></infoTributaria><infoFactura><fechaEmision>19/12/2022</fechaEmision><dirEstablecimiento>GUAYAQUIL</dirEstablecimiento><obligadoContabilidad>NO</obligadoContabilidad><tipoIdentificacionComprador>05</tipoIdentificacionComprador><razonSocialComprador>TORRES GARCIA MELBA JACQUELINE</razonSocialComprador><identificacionComprador>0902480532</identificacionComprador><totalSinImpuestos>100.85</totalSinImpuestos><totalDescuento>0</totalDescuento><totalConImpuestos><totalImpuesto><codigo>2</codigo><codigoPorcentaje>2</codigoPorcentaje><baseImponible>100.85</baseImponible><valor>12.1</valor></totalImpuesto></totalConImpuestos><propina>0.00</propina><importeTotal>112.95</importeTotal><moneda>DOLAR</moneda><pagos><pago><formaPago>01</formaPago><total>112.95</total></pago></pagos></infoFactura><detalles><detalle><codigoPrincipal>FAM.TIP.522</codigoPrincipal><descripcion>PURIFICADOR DE AGUA FILTRO DE CERAMICA</descripcion><cantidad>2</cantidad><precioUnitario>3.5</precioUnitario><descuento>0</descuento><precioTotalSinImpuesto>7</precioTotalSinImpuesto><impuestos><impuesto><codigo>2</codigo><codigoPorcentaje>2</codigoPorcentaje><tarifa>12</tarifa><baseImponible>7</baseImponible><valor>0.84</valor></impuesto></impuestos></detalle><detalle><codigoPrincipal>FAM.TIP.269</codigoPrincipal><descripcion>GANCHOS CUADRADOS</descripcion><cantidad>6</cantidad><precioUnitario>0.1</precioUnitario><descuento>0</descuento><precioTotalSinImpuesto>0.6</precioTotalSinImpuesto><impuestos><impuesto><codigo>2</codigo><codigoPorcentaje>2</codigoPorcentaje><tarifa>12</tarifa><baseImponible>0.6</baseImponible><valor>0.07</valor></impuesto></impuestos></detalle><detalle><codigoPrincipal>FAM.TIP.1465</codigoPrincipal><descripcion>LAMPARA LINEAL DE MESA</descripcion><cantidad>1</cantidad><precioUnitario>7.5</precioUnitario><descuento>0</descuento><precioTotalSinImpuesto>7.5</precioTotalSinImpuesto><impuestos><impuesto><codigo>2</codigo><codigoPorcentaje>2</codigoPorcentaje><tarifa>12</tarifa><baseImponible>7.5</baseImponible><valor>0.9</valor></impuesto></impuestos></detalle><detalle><codigoPrincipal>FAM.TIP.1369</codigoPrincipal><descripcion>1207 TRITURADOR DE VERDURAS 2 EN 1</descripcion><cantidad>1</cantidad><precioUnitario>9</precioUnitario><descuento>0</descuento><precioTotalSinImpuesto>9</precioTotalSinImpuesto><impuestos><impuesto><codigo>2</codigo><codigoPorcentaje>2</codigoPorcentaje><tarifa>12</tarifa><baseImponible>9</baseImponible><valor>1.08</valor></impuesto></impuestos></detalle><detalle><codigoPrincipal>FAM.TIP.289</codigoPrincipal><descripcion>TIRA DE LUZ LED 3528</descripcion><cantidad>1</cantidad><precioUnitario>5.25</precioUnitario><descuento>0</descuento><precioTotalSinImpuesto>5.25</precioTotalSinImpuesto><impuestos><impuesto><codigo>2</codigo><codigoPorcentaje>2</codigoPorcentaje><tarifa>12</tarifa><baseImponible>5.25</baseImponible><valor>0.63</valor></impuesto></impuestos></detalle><detalle><codigoPrincipal>FAM.TIP.300</codigoPrincipal><descripcion>VASO DE SILICONA PLEGABLE RETRACTIL</descripcion><cantidad>3</cantidad><precioUnitario>1</precioUnitario><descuento>0</descuento><precioTotalSinImpuesto>3</precioTotalSinImpuesto><impuestos><impuesto><codigo>2</codigo><codigoPorcentaje>2</codigoPorcentaje><tarifa>12</tarifa><baseImponible>3</baseImponible><valor>0.36</valor></impuesto></impuestos></detalle><detalle><codigoPrincipal>FAM.TIP.636</codigoPrincipal><descripcion>CHE-2022-4 GANCHO ORGANIZADOR GIRATORIO</descripcion><cantidad>3</cantidad><precioUnitario>1.5</precioUnitario><descuento>0</descuento><precioTotalSinImpuesto>4.5</precioTotalSinImpuesto><impuestos><impuesto><codigo>2</codigo><codigoPorcentaje>2</codigoPorcentaje><tarifa>12</tarifa><baseImponible>4.5</baseImponible><valor>0.54</valor></impuesto></impuestos></detalle><detalle><codigoPrincipal>hog.hog.010</codigoPrincipal><descripcion>ADAPTADOR DE GRIFO METALICO</descripcion><cantidad>3</cantidad><precioUnitario>1</precioUnitario><descuento>0</descuento><precioTotalSinImpuesto>3</precioTotalSinImpuesto><impuestos><impuesto><codigo>2</codigo><codigoPorcentaje>2</codigoPorcentaje><tarifa>12</tarifa><baseImponible>3</baseImponible><valor>0.36</valor></impuesto></impuestos></detalle><detalle><codigoPrincipal>FAM.TIP.776</codigoPrincipal><descripcion>FOLLAJE SINTETICO 3M</descripcion><cantidad>1</cantidad><precioUnitario>4.5</precioUnitario><descuento>0</descuento><precioTotalSinImpuesto>4.5</precioTotalSinImpuesto><impuestos><impuesto><codigo>2</codigo><codigoPorcentaje>2</codigoPorcentaje><tarifa>12</tarifa><baseImponible>4.5</baseImponible><valor>0.54</valor></impuesto></impuestos></detalle><detalle><codigoPrincipal>FAM.TIP.286</codigoPrincipal><descripcion>TABLA DE PICAR PLEGABLE</descripcion><cantidad>1</cantidad><precioUnitario>4.5</precioUnitario><descuento>0</descuento><precioTotalSinImpuesto>4.5</precioTotalSinImpuesto><impuestos><impuesto><codigo>2</codigo><codigoPorcentaje>2</codigoPorcentaje><tarifa>12</tarifa><baseImponible>4.5</baseImponible><valor>0.54</valor></impuesto></impuestos></detalle><detalle><codigoPrincipal>FAM.TIP.806</codigoPrincipal><descripcion>MONO TIPO LAZO</descripcion><cantidad>3</cantidad><precioUnitario>0.75</precioUnitario><descuento>0</descuento><precioTotalSinImpuesto>2.25</precioTotalSinImpuesto><impuestos><impuesto><codigo>2</codigo><codigoPorcentaje>2</codigoPorcentaje><tarifa>12</tarifa><baseImponible>2.25</baseImponible><valor>0.27</valor></impuesto></impuestos></detalle><detalle><codigoPrincipal>FAM.TIP.450</codigoPrincipal><descripcion>MANDOLINA PARA VERDURAS</descripcion><cantidad>1</cantidad><precioUnitario>7</precioUnitario><descuento>0</descuento><precioTotalSinImpuesto>7</precioTotalSinImpuesto><impuestos><impuesto><codigo>2</codigo><codigoPorcentaje>2</codigoPorcentaje><tarifa>12</tarifa><baseImponible>7</baseImponible><valor>0.84</valor></impuesto></impuestos></detalle><detalle><codigoPrincipal>FAM.TIP.213</codigoPrincipal><descripcion>RODILLERA DE COMPRENSION 1 UNIDAD</descripcion><cantidad>2</cantidad><precioUnitario>2.75</precioUnitario><descuento>0</descuento><precioTotalSinImpuesto>5.5</precioTotalSinImpuesto><impuestos><impuesto><codigo>2</codigo><codigoPorcentaje>2</codigoPorcentaje><tarifa>12</tarifa><baseImponible>5.5</baseImponible><valor>0.66</valor></impuesto></impuestos></detalle><detalle><codigoPrincipal>FAM.TIP.301</codigoPrincipal><descripcion>CAMARA EXTERIOR IP66 APP YILOT</descripcion><cantidad>1</cantidad><precioUnitario>19</precioUnitario><descuento>0</descuento><precioTotalSinImpuesto>19</precioTotalSinImpuesto><impuestos><impuesto><codigo>2</codigo><codigoPorcentaje>2</codigoPorcentaje><tarifa>12</tarifa><baseImponible>19</baseImponible><valor>2.28</valor></impuesto></impuestos></detalle><detalle><codigoPrincipal>FAM.TIP.282</codigoPrincipal><descripcion>RELOJ HEXAGONAL DE LUCES A PILAS</descripcion><cantidad>3</cantidad><precioUnitario>2.25</precioUnitario><descuento>0</descuento><precioTotalSinImpuesto>6.75</precioTotalSinImpuesto><impuestos><impuesto><codigo>2</codigo><codigoPorcentaje>2</codigoPorcentaje><tarifa>12</tarifa><baseImponible>6.75</baseImponible><valor>0.81</valor></impuesto></impuestos></detalle><detalle><codigoPrincipal>FAM.TIP.460</codigoPrincipal><descripcion>FOCO HUMIDIFICADOR</descripcion><cantidad>1</cantidad><precioUnitario>4</precioUnitario><descuento>0</descuento><precioTotalSinImpuesto>4</precioTotalSinImpuesto><impuestos><impuesto><codigo>2</codigo><codigoPorcentaje>2</codigoPorcentaje><tarifa>12</tarifa><baseImponible>4</baseImponible><valor>0.48</valor></impuesto></impuestos></detalle><detalle><codigoPrincipal>FAM.TIP.893</codigoPrincipal><descripcion>ALFOMBRAS DE COCINA</descripcion><cantidad>1</cantidad><precioUnitario>4.25</precioUnitario><descuento>0</descuento><precioTotalSinImpuesto>4.25</precioTotalSinImpuesto><impuestos><impuesto><codigo>2</codigo><codigoPorcentaje>2</codigoPorcentaje><tarifa>12</tarifa><baseImponible>4.25</baseImponible><valor>0.51</valor></impuesto></impuestos></detalle><detalle><codigoPrincipal>FAM.TIP.677</codigoPrincipal><descripcion>CINTA ADHESIVA DOBLE FAZ 1M</descripcion><cantidad>1</cantidad><precioUnitario>1.75</precioUnitario><descuento>0</descuento><precioTotalSinImpuesto>1.75</precioTotalSinImpuesto><impuestos><impuesto><codigo>2</codigo><codigoPorcentaje>2</codigoPorcentaje><tarifa>12</tarifa><baseImponible>1.75</baseImponible><valor>0.21</valor></impuesto></impuestos></detalle><detalle><codigoPrincipal>FAM.TIP.1087</codigoPrincipal><descripcion>CINTA DECORATIVA IMPERMEABLE PARA COCINA Y BANO</descripcion><cantidad>1</cantidad><precioUnitario>1.5</precioUnitario><descuento>0</descuento><precioTotalSinImpuesto>1.5</precioTotalSinImpuesto><impuestos><impuesto><codigo>2</codigo><codigoPorcentaje>2</codigoPorcentaje><tarifa>12</tarifa><baseImponible>1.5</baseImponible><valor>0.18</valor></impuesto></impuestos></detalle></detalles><infoAdicional><campoAdicional nombre='Direccion'>GUAYAQUIL</campoAdicional><campoAdicional nombre='Telefono'>0999999</campoAdicional><campoAdicional nombre='Email'>amazot@gmail.com</campoAdicional></infoAdicional></factura>